quality_result_gui/__init__.py
quality_result_gui/env.py
quality_result_gui/layer_mapping.py
quality_result_gui/py.typed
quality_result_gui/quality_data_fetcher.py
quality_result_gui/quality_error_manager.py
quality_result_gui/quality_error_manager_settings.py
quality_result_gui/quality_error_visualizer.py
quality_result_gui/quality_errors_filters.py
quality_result_gui/quality_errors_tree_model.py
quality_result_gui/quality_layer.py
quality_result_gui/api/__init__.py
quality_result_gui/api/quality_api_client.py
quality_result_gui/api/types/__init__.py
quality_result_gui/api/types/quality_error.py
quality_result_gui/configuration/__init__.py
quality_result_gui/resources/__init__.py
quality_result_gui/resources/icons/quality_error_fatal.svg
quality_result_gui/resources/icons/quality_error_info.svg
quality_result_gui/resources/icons/quality_error_warning.svg
quality_result_gui/resources/icons/quality_result_gui.svg
quality_result_gui/style/__init__.py
quality_result_gui/style/default_style.py
quality_result_gui/style/quality_layer_error_symbol.py
quality_result_gui/ui/__init__.py
quality_result_gui/ui/quality_error_tree_view.py
quality_result_gui/ui/quality_errors_dock.py
quality_result_gui/ui/quality_errors_dock.ui
quality_result_gui/ui/quality_errors_tree_filter_menu.py
quality_result_gui/utils/__init__.py
quality_result_gui/utils/layer_utils.py
quality_result_gui/utils/styling_utils.py
quality_result_gui_plugin/__init__.py
quality_result_gui_plugin/metadata.txt
quality_result_gui_plugin/plugin.py
quality_result_gui_plugin/py.typed
quality_result_gui_plugin/dev_tools/__init__.py
quality_result_gui_plugin/dev_tools/dev_tools_dialog.py
quality_result_gui_plugin/dev_tools/dev_tools_dialog.ui
quality_result_gui_plugin/dev_tools/mock_api_client.py
quality_result_gui_plugin/dev_tools/response_parser.py
quality_result_gui_plugin/dev_tools/example_quality_errors/quality_errors.json
quality_result_gui_plugin/dev_tools/example_quality_errors/quality_errors_from_conftest.json
quality_result_gui-2.0.8.dist-info/LICENSE
quality_result_gui-2.0.8.dist-info/METADATA
quality_result_gui-2.0.8.dist-info/WHEEL
quality_result_gui-2.0.8.dist-info/entry_points.txt
quality_result_gui-2.0.8.dist-info/top_level.txt
quality_result_gui-2.0.8.dist-info/RECORD
