Metadata-Version: 2.1
Name: quality-result-gui
Version: 2.0.8
Summary: QGIS plugin for visualizing quality check results.
Home-page: https://github.com/nlsfi/quality-result-gui
Author: National Land Survey of Finland
Author-email: os@nls.fi
License: GNU GPL v3.0
Project-URL: Changelog, https://github.com/nlsfi/quality-result-gui/blob/main/CHANGELOG.md
Keywords: qgis
Classifier: Development Status :: 3 - Alpha
Classifier: License :: OSI Approved :: GNU General Public License v3 (GPLv3)
Classifier: Operating System :: OS Independent
Classifier: Programming Language :: Python :: 3 :: Only
Classifier: Programming Language :: Python :: Implementation :: CPython
Classifier: Topic :: Software Development :: Libraries
Classifier: Typing :: Typed
License-File: LICENSE
Requires-Dist: qgis-plugin-tools >=0.2.0
